LICENSE
MANIFEST.in
README.md
VERSION
pyproject.toml
requirements.txt
setup.py
covalent_cloud/__init__.py
covalent_cloud.egg-info/PKG-INFO
covalent_cloud.egg-info/SOURCES.txt
covalent_cloud.egg-info/dependency_links.txt
covalent_cloud.egg-info/requires.txt
covalent_cloud.egg-info/top_level.txt
covalent_cloud/analytics/__init__.py
covalent_cloud/cloud_executor/__init__.py
covalent_cloud/cloud_executor/cloud_executor.py
covalent_cloud/cloud_executor/oci_cloud_executor.py
covalent_cloud/cloud_executor/models/__init__.py
covalent_cloud/cloud_executor/models/gpu.py
covalent_cloud/cloud_executor/models/sw_environment.py
covalent_cloud/dispatch_management/__init__.py
covalent_cloud/dispatch_management/dispatch_info.py
covalent_cloud/dispatch_management/helpers.py
covalent_cloud/dispatch_management/interface_functions.py
covalent_cloud/dispatch_management/results_manager.py
covalent_cloud/function_serve/__init__.py
covalent_cloud/function_serve/assets.py
covalent_cloud/function_serve/client.py
covalent_cloud/function_serve/common.py
covalent_cloud/function_serve/decorators.py
covalent_cloud/function_serve/deployment.py
covalent_cloud/function_serve/models.py
covalent_cloud/function_serve/service_class.py
covalent_cloud/service_account_interface/__init__.py
covalent_cloud/service_account_interface/auth_config_manager.py
covalent_cloud/service_account_interface/client.py
covalent_cloud/shared/__init__.py
covalent_cloud/shared/classes/__init__.py
covalent_cloud/shared/classes/api.py
covalent_cloud/shared/classes/exceptions.py
covalent_cloud/shared/classes/helpers.py
covalent_cloud/shared/classes/settings.py
covalent_cloud/shared/schemas/__init__.py
covalent_cloud/shared/schemas/volume.py
covalent_cloud/software_environment/__init__.py
covalent_cloud/swe_management/__init__.py
covalent_cloud/swe_management/secrets_manager.py
covalent_cloud/swe_management/swe_manager.py
covalent_cloud/swe_management/models/__init__.py
covalent_cloud/swe_management/models/environment.py
covalent_cloud/volume/__init__.py
covalent_cloud/volume/volume.py
tests/dispatch_management_tests/__init__.py
tests/dispatch_management_tests/future_classes_test.py
