Metadata-Version: 2.1
Name: covalent-cloud
Version: 1.2.0
Summary: Covalent Cloud SDK
Home-page: https://github.com/AgnostiqHQ/covalent-cloud-sdk
Download-URL: https://github.com/AgnostiqHQ/covalent-cloud-sdk/archive/v1.2.0.tar.gz
Author: Agnostiq
Author-email: support@agnostiq.ai
Maintainer: Agnostiq
License: Apache License 2.0
Classifier: Development Status :: 4 - Beta
Classifier: Environment :: Console
Classifier: Environment :: Plugins
Classifier: Intended Audience :: Developers
Classifier: Intended Audience :: Education
Classifier: Intended Audience :: Science/Research
Classifier: License :: Other/Proprietary License
Classifier: Natural Language :: English
Classifier: Operating System :: MacOS
Classifier: Operating System :: POSIX :: Linux
Classifier: Programming Language :: Python :: 3
Classifier: Programming Language :: Python :: 3 :: Only
Classifier: Programming Language :: Python :: 3.8
Classifier: Programming Language :: Python :: 3.9
Classifier: Topic :: Adaptive Technologies
Classifier: Topic :: Scientific/Engineering
Classifier: Topic :: Scientific/Engineering :: Interface Engine/Protocol Translator
Classifier: Topic :: Software Development
Classifier: Topic :: System :: Distributed Computing
Requires-Python: >=3.8
License-File: LICENSE
